setup.py
dsnd_distributions_ah_test/Binomialdistribution.py
dsnd_distributions_ah_test/Gaussiandistribution.py
dsnd_distributions_ah_test/Generaldistribution.py
dsnd_distributions_ah_test/__init__.py
dsnd_distributions_ah_test.egg-info/PKG-INFO
dsnd_distributions_ah_test.egg-info/SOURCES.txt
dsnd_distributions_ah_test.egg-info/dependency_links.txt
dsnd_distributions_ah_test.egg-info/not-zip-safe
dsnd_distributions_ah_test.egg-info/top_level.txt