Metadata-Version: 1.0
Name: dsnd-distributions-ah-test
Version: 0.1
Summary: Gaussian and Binomial distributions
Home-page: UNKNOWN
Author: Alejandro Hohmann
Author-email: alejandrohohmann@gmail.com
License: UNKNOWN
Platform: UNKNOWN
